ufbt/__init__.py
ufbt/__main__.py
ufbt/bootstrap.py
ufbt-0.2.6.dist-info/LICENSE.md
ufbt-0.2.6.dist-info/METADATA
ufbt-0.2.6.dist-info/WHEEL
ufbt-0.2.6.dist-info/entry_points.txt
ufbt-0.2.6.dist-info/top_level.txt
ufbt-0.2.6.dist-info/RECORD
