Metadata-Version: 2.1
Name: ufbt
Version: 0.2.6
Summary: uFBT - micro Flipper Build Tool. Tool for building and developing applications (.fap) for Flipper Zero and its device family.
Author-email: "Flipper Devices Inc." <pypi@flipperdevices.com>
License: GPL-3.0
Project-URL: homepage, https://github.com/flipperdevices/flipperzero-ufbt
Project-URL: documentation, https://github.com/flipperdevices/flipperzero-ufbt
Project-URL: repository, https://github.com/flipperdevices/flipperzero-ufbt
Project-URL: issues, https://github.com/flipperdevices/flipperzero-ufbt/issues
Keywords: ufbt,flipperzero,fbt,stm32,fap
Classifier: Programming Language :: Python :: 3
Classifier: Programming Language :: C
Classifier: Intended Audience :: Developers
Classifier: License :: OSI Approved :: GNU General Public License v3 or later (GPLv3+)
Classifier: Topic :: Software Development :: Build Tools
Classifier: Topic :: Software Development :: Compilers
Classifier: Topic :: Software Development :: Embedded Systems
Classifier: Development Status :: 4 - Beta
Classifier: Environment :: Console
Classifier: Operating System :: MacOS
Classifier: Operating System :: Microsoft :: Windows
Classifier: Operating System :: POSIX :: Linux
Requires-Python: >=3.8
License-File: LICENSE.md
Requires-Dist: oslex>=0.1.3
